<?xml version="1.0" encoding="utf-8"?>
<fmg>
<compression>None</compression>
<version>DarkSouls3</version>
<bigendian>False</bigendian>
<entries>
<text id="744">One of the twisted souls, steeped in strength</text>
<text id="2153">Burn at Firelink Shrine to unlock Undead Matches</text>
<text id="2154">Shrine handmaid will prepare new items</text>
<text id="2155">Key to the contraption accessing the library attic</text>
<text id="1313000">Imbues right-hand weapon with frost</text>
<text id="1313010">Imbues right-hand weapon with frost</text>
<text id="1741000">Creates cloud of near-freezing mist</text>
<text id="1741010">Creates lingering cloud of near-freezing mist</text>
<text id="2457000">Summons fire-spitting chaos orb</text>
<text id="2457010">Summons fire-spitting chaos orb</text>
<text id="3556000">White discus slices into foes and returns to conjurer</text>
<text id="3556010">White discus slices into foes and returns to conjurer with no focus cost</text>
</entries>
</fmg>