<?xml version="1.0" encoding="utf-8"?>
<fmg>
<compression>None</compression>
<version>DarkSouls3</version>
<bigendian>False</bigendian>
<entries>
<text id="1">%null%</text>
<text id="2">%null%</text>
<text id="100">Havel's Ring</text>
<text id="101">Red Tearstone Ring</text>
<text id="102">Darkmoon Blade Covenant Ring</text>
<text id="103">Cat Covenant Ring</text>
<text id="104">Cloranthy Ring</text>
<text id="105">Flame Stoneplate Ring</text>
<text id="106">Thunder Stoneplate Ring</text>
<text id="107">Spell Stoneplate Ring</text>
<text id="108">Speckled Stoneplate Ring</text>
<text id="109">Bloodbite Ring</text>
<text id="110">Poisonbite Ring</text>
<text id="111">Tiny Being's Ring</text>
<text id="112">%null%</text>
<text id="113">Cursebite Ring</text>
<text id="114">White Seance Ring</text>
<text id="115">Bellowing Dragoncrest Ring</text>
<text id="116">Dusk Crown Ring</text>
<text id="117">Hornet Ring</text>
<text id="118">%null%</text>
<text id="119">Hawk Ring</text>
<text id="120">Ring of Steel Protection</text>
<text id="121">Covetous Gold Serpent Ring</text>
<text id="122">Covetous Silver Serpent Ring</text>
<text id="123">Slumbering Dragoncrest Ring</text>
<text id="124">Ring of Fog</text>
<text id="125">Rusted Iron Ring</text>
<text id="126">Ring of Sacrifice</text>
<text id="127">Rare Ring of Sacrifice</text>
<text id="128">Dark Wood Grain Ring</text>
<text id="129">%null%</text>
<text id="130">Ring of the Sun Princess</text>
<text id="131">%null%</text>
<text id="132">%null%</text>
<text id="133">Ring of Condemnation</text>
<text id="134">Ring of Blind Ghosts</text>
<text id="135">%null%</text>
<text id="136">%null%</text>
<text id="137">Old Witch's Ring</text>
<text id="138">Covenant of Artorias</text>
<text id="139">Orange Charred Ring</text>
<text id="140">Ring of Displacement</text>
<text id="141">Lingering Dragoncrest Ring</text>
<text id="142">Ring of the Evil Eye</text>
<text id="143">Ring of Favor and Protection</text>
<text id="144">Leo Ring</text>
<text id="145">East Wood Grain Ring</text>
<text id="146">Wolf Ring</text>
<text id="147">Blue Tearstone Ring</text>
<text id="148">Ring of the Sun's Firstborn</text>
<text id="149">Darkmoon Seance Ring</text>
<text id="160">%null%</text>
<text id="161">%null%</text>
<text id="162">%null%</text>
<text id="10000">Darkmoon Faithful</text>
<text id="10020">Watchdogs of Farron</text>
<text id="10030">Aldrich Faithful</text>
<text id="10040">Warrior of Sunlight</text>
<text id="10050">Mound-makers</text>
<text id="10060">Thieves' Pact</text>
<text id="10070">Chaos Servant</text>
<text id="10080">Rosaria's Fingers</text>
<text id="10100">Vinheim Scholars</text>
<text id="10110">Pilgrims of Dark</text>
<text id="10120">Way of White</text>
<text id="10130">Dragon Remnants</text>
<text id="10140">Blue Sentinels</text>
<text id="10150">Way of Blue</text>
<text id="10160">Company of Champions</text>
<text id="10170">Servant of the Rat</text>
<text id="10180">Ritualist Pact</text>
<text id="20000">Life Ring</text>
<text id="20001">Life Ring+1</text>
<text id="20002">Life Ring+2</text>
<text id="20003">Life Ring+3</text>
<text id="20004">Life Ring+4</text>
<text id="20005">Life Ring+5</text>
<text id="20006">%null%</text>
<text id="20007">%null%</text>
<text id="20008">%null%</text>
<text id="20009">%null%</text>
<text id="20010">Chloranthy Ring</text>
<text id="20011">Chloranthy Ring+1</text>
<text id="20012">Chloranthy Ring+2</text>
<text id="20013">Chloranthy Ring+3</text>
<text id="20014">Chloranthy Ring+4</text>
<text id="20015">Chloranthy Ring+5</text>
<text id="20016">%null%</text>
<text id="20017">%null%</text>
<text id="20018">%null%</text>
<text id="20019">%null%</text>
<text id="20020">Havel's Ring</text>
<text id="20021">Havel's Ring+1</text>
<text id="20022">Havel's Ring+2</text>
<text id="20023">Havel's Ring+3</text>
<text id="20024">Havel's Ring+4</text>
<text id="20025">Havel's Ring+5</text>
<text id="20026">%null%</text>
<text id="20027">%null%</text>
<text id="20028">%null%</text>
<text id="20029">%null%</text>
<text id="20030">Ring of Favor</text>
<text id="20031">Ring of Favor+1</text>
<text id="20032">Ring of Favor+2</text>
<text id="20033">Ring of Favor+3</text>
<text id="20034">Ring of Favor+4</text>
<text id="20035">Ring of Favor+5</text>
<text id="20036">%null%</text>
<text id="20037">%null%</text>
<text id="20038">%null%</text>
<text id="20039">%null%</text>
<text id="20040">Ring of Steel Protection</text>
<text id="20041">Ring of Steel Protection+1</text>
<text id="20042">Ring of Steel Protection+2</text>
<text id="20043">Ring of Steel Protection+3</text>
<text id="20044">Ring of Steel Protection+4</text>
<text id="20045">Ring of Steel Protection+5</text>
<text id="20046">%null%</text>
<text id="20047">%null%</text>
<text id="20048">%null%</text>
<text id="20049">%null%</text>
<text id="20050">Flame Stoneplate Ring</text>
<text id="20051">Flame Stoneplate Ring+1</text>
<text id="20052">Flame Stoneplate Ring+2</text>
<text id="20053">Flame Stoneplate Ring+3</text>
<text id="20054">Flame Stoneplate Ring+4</text>
<text id="20055">Flame Stoneplate Ring+5</text>
<text id="20056">%null%</text>
<text id="20057">%null%</text>
<text id="20058">%null%</text>
<text id="20059">%null%</text>
<text id="20060">Thunder Stoneplate Ring</text>
<text id="20061">Thunder Stoneplate Ring+1</text>
<text id="20062">Thunder Stoneplate Ring+2</text>
<text id="20063">Thunder Stoneplate Ring+3</text>
<text id="20064">Thunder Stoneplate Ring+4</text>
<text id="20065">Thunder Stoneplate Ring+5</text>
<text id="20066">%null%</text>
<text id="20067">%null%</text>
<text id="20068">%null%</text>
<text id="20069">%null%</text>
<text id="20070">Magic Stoneplate Ring</text>
<text id="20071">Magic Stoneplate Ring+1</text>
<text id="20072">Magic Stoneplate Ring+2</text>
<text id="20073">Magic Stoneplate Ring+3</text>
<text id="20074">Magic Stoneplate Ring+4</text>
<text id="20075">Magic Stoneplate Ring+5</text>
<text id="20076">%null%</text>
<text id="20077">%null%</text>
<text id="20078">%null%</text>
<text id="20079">%null%</text>
<text id="20080">Dark Stoneplate Ring</text>
<text id="20081">Dark Stoneplate Ring+1</text>
<text id="20082">Dark Stoneplate Ring+2</text>
<text id="20083">Dark Stoneplate Ring+3</text>
<text id="20084">Dark Stoneplate Ring+4</text>
<text id="20085">Dark Stoneplate Ring+5</text>
<text id="20086">%null%</text>
<text id="20087">%null%</text>
<text id="20088">%null%</text>
<text id="20089">%null%</text>
<text id="20090">Speckled Stoneplate Ring</text>
<text id="20091">Speckled Stoneplate Ring+1</text>
<text id="20092">Speckled Stoneplate Ring+2</text>
<text id="20093">Speckled Stoneplate Ring+3</text>
<text id="20094">Speckled Stoneplate Ring+4</text>
<text id="20095">Speckled Stoneplate Ring+5</text>
<text id="20096">%null%</text>
<text id="20097">%null%</text>
<text id="20098">%null%</text>
<text id="20099">%null%</text>
<text id="20100">Bloodbite Ring</text>
<text id="20101">Bloodbite Ring+1</text>
<text id="20102">Bloodbite Ring+2</text>
<text id="20103">Bloodbite Ring+3</text>
<text id="20104">Bloodbite Ring+4</text>
<text id="20105">Bloodbite Ring+5</text>
<text id="20106">%null%</text>
<text id="20107">%null%</text>
<text id="20108">%null%</text>
<text id="20109">%null%</text>
<text id="20110">Poisonbite Ring</text>
<text id="20111">Poisonbite Ring+1</text>
<text id="20112">Poisonbite Ring+2</text>
<text id="20113">Poisonbite Ring+3</text>
<text id="20114">Poisonbite Ring+4</text>
<text id="20115">Poisonbite Ring+5</text>
<text id="20116">%null%</text>
<text id="20117">%null%</text>
<text id="20118">%null%</text>
<text id="20119">%null%</text>
<text id="20120">Cursebite Ring</text>
<text id="20121">Cursebite Ring+1</text>
<text id="20122">Cursebite Ring+2</text>
<text id="20123">Cursebite Ring+3</text>
<text id="20124">Cursebite Ring+4</text>
<text id="20125">Cursebite Ring+5</text>
<text id="20126">%null%</text>
<text id="20127">%null%</text>
<text id="20128">%null%</text>
<text id="20129">%null%</text>
<text id="20130">Fleshbite Ring</text>
<text id="20131">Fleshbite Ring+1</text>
<text id="20132">Fleshbite Ring+2</text>
<text id="20133">Fleshbite Ring+3</text>
<text id="20134">Fleshbite Ring+4</text>
<text id="20135">Fleshbite Ring+5</text>
<text id="20136">%null%</text>
<text id="20137">%null%</text>
<text id="20138">%null%</text>
<text id="20139">%null%</text>
<text id="20140">Wood Grain Ring</text>
<text id="20141">Wood Grain Ring+1</text>
<text id="20142">Wood Grain Ring+2</text>
<text id="20143">Wood Grain Ring+3</text>
<text id="20144">Wood Grain Ring+4</text>
<text id="20145">Wood Grain Ring+5</text>
<text id="20146">%null%</text>
<text id="20147">%null%</text>
<text id="20148">%null%</text>
<text id="20149">%null%</text>
<text id="20150">Scholar Ring</text>
<text id="20151">Scholar Ring+1</text>
<text id="20152">Scholar Ring+2</text>
<text id="20153">Scholar Ring+3</text>
<text id="20154">Scholar Ring+4</text>
<text id="20155">Scholar Ring+5</text>
<text id="20156">%null%</text>
<text id="20157">%null%</text>
<text id="20158">%null%</text>
<text id="20159">%null%</text>
<text id="20160">Priestess Ring</text>
<text id="20161">Priestess Ring+1</text>
<text id="20162">Priestess Ring+2</text>
<text id="20163">Priestess Ring+3</text>
<text id="20164">Priestess Ring+4</text>
<text id="20165">Priestess Ring+5</text>
<text id="20166">%null%</text>
<text id="20167">%null%</text>
<text id="20168">%null%</text>
<text id="20169">%null%</text>
<text id="20170">Red Tearstone Ring</text>
<text id="20171">Red Tearstone Ring+1</text>
<text id="20172">Red Tearstone Ring+2</text>
<text id="20173">Red Tearstone Ring+3</text>
<text id="20174">Red Tearstone Ring+4</text>
<text id="20175">Red Tearstone Ring+5</text>
<text id="20176">%null%</text>
<text id="20177">%null%</text>
<text id="20178">%null%</text>
<text id="20179">%null%</text>
<text id="20180">Blue Tearstone Ring</text>
<text id="20181">Blue Tearstone Ring+1</text>
<text id="20182">Blue Tearstone Ring+2</text>
<text id="20183">Blue Tearstone Ring+3</text>
<text id="20184">Blue Tearstone Ring+4</text>
<text id="20185">Blue Tearstone Ring+5</text>
<text id="20186">%null%</text>
<text id="20187">%null%</text>
<text id="20188">%null%</text>
<text id="20189">%null%</text>
<text id="20190">Wolf Ring</text>
<text id="20191">Wolf Ring+1</text>
<text id="20192">Wolf Ring+2</text>
<text id="20193">Wolf Ring+3</text>
<text id="20194">Wolf Ring+4</text>
<text id="20195">Wolf Ring+5</text>
<text id="20196">%null%</text>
<text id="20197">%null%</text>
<text id="20198">%null%</text>
<text id="20199">%null%</text>
<text id="20200">Leo Ring</text>
<text id="20201">%null%</text>
<text id="20202">%null%</text>
<text id="20203">%null%</text>
<text id="20204">%null%</text>
<text id="20205">%null%</text>
<text id="20206">%null%</text>
<text id="20207">%null%</text>
<text id="20208">%null%</text>
<text id="20209">%null%</text>
<text id="20210">Ring of Sacrifice</text>
<text id="20211">%null%</text>
<text id="20212">%null%</text>
<text id="20213">%null%</text>
<text id="20214">%null%</text>
<text id="20215">%null%</text>
<text id="20216">%null%</text>
<text id="20217">%null%</text>
<text id="20218">%null%</text>
<text id="20219">%null%</text>
<text id="20220">Rare Ring of Sacrifice</text>
<text id="20221">%null%</text>
<text id="20222">%null%</text>
<text id="20223">%null%</text>
<text id="20224">%null%</text>
<text id="20225">%null%</text>
<text id="20226">%null%</text>
<text id="20227">%null%</text>
<text id="20228">%null%</text>
<text id="20229">%null%</text>
<text id="20230">Young Dragon Ring</text>
<text id="20231">%null%</text>
<text id="20232">%null%</text>
<text id="20233">%null%</text>
<text id="20234">%null%</text>
<text id="20235">%null%</text>
<text id="20236">%null%</text>
<text id="20237">%null%</text>
<text id="20238">%null%</text>
<text id="20239">%null%</text>
<text id="20240">Great Swamp Ring</text>
<text id="20241">%null%</text>
<text id="20242">%null%</text>
<text id="20243">%null%</text>
<text id="20244">%null%</text>
<text id="20245">%null%</text>
<text id="20246">%null%</text>
<text id="20247">%null%</text>
<text id="20248">%null%</text>
<text id="20249">%null%</text>
<text id="20250">Morne's Ring</text>
<text id="20251">%null%</text>
<text id="20252">%null%</text>
<text id="20253">%null%</text>
<text id="20254">%null%</text>
<text id="20255">%null%</text>
<text id="20256">%null%</text>
<text id="20257">%null%</text>
<text id="20258">%null%</text>
<text id="20259">%null%</text>
<text id="20260">%null%</text>
<text id="20261">%null%</text>
<text id="20262">%null%</text>
<text id="20263">%null%</text>
<text id="20264">%null%</text>
<text id="20265">%null%</text>
<text id="20266">%null%</text>
<text id="20267">%null%</text>
<text id="20268">%null%</text>
<text id="20269">%null%</text>
<text id="20270">Lingering Dragoncrest Ring</text>
<text id="20271">Lingering Dragoncrest Ring+1</text>
<text id="20272">Lingering Dragoncrest Ring+2</text>
<text id="20273">Lingering Dragoncrest Ring+3</text>
<text id="20274">Lingering Dragoncrest Ring+4</text>
<text id="20275">Lingering Dragoncrest Ring+5</text>
<text id="20276">%null%</text>
<text id="20277">%null%</text>
<text id="20278">%null%</text>
<text id="20279">%null%</text>
<text id="20280">Sage Ring</text>
<text id="20281">Sage Ring+1</text>
<text id="20282">Sage Ring+2</text>
<text id="20283">Sage Ring+3</text>
<text id="20284">Sage Ring+4</text>
<text id="20285">Sage Ring+5</text>
<text id="20286">%null%</text>
<text id="20287">%null%</text>
<text id="20288">%null%</text>
<text id="20289">%null%</text>
<text id="20290">Slumbering Dragoncrest Ring</text>
<text id="20291">%null%</text>
<text id="20292">%null%</text>
<text id="20293">%null%</text>
<text id="20294">%null%</text>
<text id="20295">%null%</text>
<text id="20296">%null%</text>
<text id="20297">%null%</text>
<text id="20298">%null%</text>
<text id="20299">%null%</text>
<text id="20300">Dusk Crown Ring</text>
<text id="20301">Dusk Crown Ring+1</text>
<text id="20302">Dusk Crown Ring+2</text>
<text id="20303">Dusk Crown Ring+3</text>
<text id="20304">Dusk Crown Ring+4</text>
<text id="20305">Dusk Crown Ring+5</text>
<text id="20306">%null%</text>
<text id="20307">%null%</text>
<text id="20308">%null%</text>
<text id="20309">%null%</text>
<text id="20310">Saint's Ring</text>
<text id="20311">%null%</text>
<text id="20312">%null%</text>
<text id="20313">%null%</text>
<text id="20314">%null%</text>
<text id="20315">%null%</text>
<text id="20316">%null%</text>
<text id="20317">%null%</text>
<text id="20318">%null%</text>
<text id="20319">%null%</text>
<text id="20320">Deep Ring</text>
<text id="20321">%null%</text>
<text id="20322">%null%</text>
<text id="20323">%null%</text>
<text id="20324">%null%</text>
<text id="20325">%null%</text>
<text id="20326">%null%</text>
<text id="20327">%null%</text>
<text id="20328">%null%</text>
<text id="20329">%null%</text>
<text id="20330">Darkmoon Ring</text>
<text id="20331">Darkmoon Ring+1</text>
<text id="20332">Darkmoon Ring+2</text>
<text id="20333">Darkmoon Ring+3</text>
<text id="20334">Darkmoon Ring+4</text>
<text id="20335">Darkmoon Ring+5</text>
<text id="20336">%null%</text>
<text id="20337">%null%</text>
<text id="20338">%null%</text>
<text id="20339">%null%</text>
<text id="20340">Bellowing Dragoncrest Ring</text>
<text id="20341">Bellowing Dragoncrest Ring+1</text>
<text id="20342">Bellowing Dragoncrest Ring+2</text>
<text id="20343">Bellowing Dragoncrest Ring+3</text>
<text id="20344">Bellowing Dragoncrest Ring+4</text>
<text id="20345">Bellowing Dragoncrest Ring+5</text>
<text id="20346">%null%</text>
<text id="20347">%null%</text>
<text id="20348">%null%</text>
<text id="20349">%null%</text>
<text id="20350">Witch's Ring</text>
<text id="20351">Witch's Ring+1</text>
<text id="20352">Witch's Ring+2</text>
<text id="20353">Witch's Ring+3</text>
<text id="20354">Witch's Ring+4</text>
<text id="20355">Witch's Ring+5</text>
<text id="20356">%null%</text>
<text id="20357">%null%</text>
<text id="20358">%null%</text>
<text id="20359">%null%</text>
<text id="20360">Ring of the Sun's First Born</text>
<text id="20361">Ring of the Sun's First Born+1</text>
<text id="20362">Ring of the Sun's First Born+2</text>
<text id="20363">Ring of the Sun's First Born+3</text>
<text id="20364">Ring of the Sun's First Born+4</text>
<text id="20365">Ring of the Sun's First Born+5</text>
<text id="20366">%null%</text>
<text id="20367">%null%</text>
<text id="20368">%null%</text>
<text id="20369">%null%</text>
<text id="20370">Hawk Ring</text>
<text id="20371">Hawk Ring+1</text>
<text id="20372">Hawk Ring+2</text>
<text id="20373">Hawk Ring+3</text>
<text id="20374">Hawk Ring+4</text>
<text id="20375">Hawk Ring+5</text>
<text id="20376">%null%</text>
<text id="20377">%null%</text>
<text id="20378">%null%</text>
<text id="20379">%null%</text>
<text id="20380">Hornet Ring</text>
<text id="20381">%null%</text>
<text id="20382">%null%</text>
<text id="20383">%null%</text>
<text id="20384">%null%</text>
<text id="20385">%null%</text>
<text id="20386">%null%</text>
<text id="20387">%null%</text>
<text id="20388">%null%</text>
<text id="20389">%null%</text>
<text id="20390">Covetous Gold Serpent Ring</text>
<text id="20391">Covetous Gold Serpent Ring+1</text>
<text id="20392">Covetous Gold Serpent Ring+2</text>
<text id="20393">Covetous Gold Serpent Ring+3</text>
<text id="20394">Covetous Gold Serpent Ring+4</text>
<text id="20395">Covetous Gold Serpent Ring+5</text>
<text id="20396">%null%</text>
<text id="20397">%null%</text>
<text id="20398">%null%</text>
<text id="20399">%null%</text>
<text id="20400">Covetous Silver Serpent Ring</text>
<text id="20401">Covetous Silver Serpent Ring+1</text>
<text id="20402">Covetous Silver Serpent Ring+2</text>
<text id="20403">Covetous Silver Serpent Ring+3</text>
<text id="20404">Covetous Silver Serpent Ring+4</text>
<text id="20405">Covetous Silver Serpent Ring+5</text>
<text id="20406">%null%</text>
<text id="20407">%null%</text>
<text id="20408">%null%</text>
<text id="20409">%null%</text>
<text id="20410">Sun Princess Ring</text>
<text id="20411">Sun Princess Ring+1</text>
<text id="20412">Sun Princess Ring+2</text>
<text id="20413">Sun Princess Ring+3</text>
<text id="20414">Sun Princess Ring+4</text>
<text id="20415">Sun Princess Ring+5</text>
<text id="20416">%null%</text>
<text id="20417">%null%</text>
<text id="20418">%null%</text>
<text id="20419">%null%</text>
<text id="20420">Silvercat Ring</text>
<text id="20421">%null%</text>
<text id="20422">%null%</text>
<text id="20423">%null%</text>
<text id="20424">%null%</text>
<text id="20425">%null%</text>
<text id="20426">%null%</text>
<text id="20427">%null%</text>
<text id="20428">%null%</text>
<text id="20429">%null%</text>
<text id="20430">Skull Ring</text>
<text id="20431">Skull Ring+1</text>
<text id="20432">Skull Ring+2</text>
<text id="20433">Skull Ring+3</text>
<text id="20434">Skull Ring+4</text>
<text id="20435">Skull Ring+5</text>
<text id="20436">%null%</text>
<text id="20437">%null%</text>
<text id="20438">%null%</text>
<text id="20439">%null%</text>
<text id="20440">%null%</text>
<text id="20441">%null%</text>
<text id="20442">%null%</text>
<text id="20443">%null%</text>
<text id="20444">%null%</text>
<text id="20445">%null%</text>
<text id="20446">%null%</text>
<text id="20447">%null%</text>
<text id="20448">%null%</text>
<text id="20449">%null%</text>
<text id="20450">Carthus Milkring</text>
<text id="20451">%null%</text>
<text id="20452">%null%</text>
<text id="20453">%null%</text>
<text id="20454">%null%</text>
<text id="20455">%null%</text>
<text id="20456">%null%</text>
<text id="20457">%null%</text>
<text id="20458">%null%</text>
<text id="20459">%null%</text>
<text id="20460">Knight's Ring</text>
<text id="20461">Knight's Ring+1</text>
<text id="20462">Knight's Ring+2</text>
<text id="20463">Knight's Ring+3</text>
<text id="20464">Knight's Ring+4</text>
<text id="20465">Knight's Ring+5</text>
<text id="20466">%null%</text>
<text id="20467">%null%</text>
<text id="20468">%null%</text>
<text id="20469">%null%</text>
<text id="20470">Hunter's Ring</text>
<text id="20471">Hunter's Ring+1</text>
<text id="20472">Hunter's Ring+2</text>
<text id="20473">Hunter's Ring+3</text>
<text id="20474">Hunter's Ring+4</text>
<text id="20475">Hunter's Ring+5</text>
<text id="20476">%null%</text>
<text id="20477">%null%</text>
<text id="20478">%null%</text>
<text id="20479">%null%</text>
<text id="20480">Knight Slayer's Ring</text>
<text id="20481">Knight Slayer's Ring+1</text>
<text id="20482">Knight Slayer's Ring+2</text>
<text id="20483">Knight Slayer's Ring+3</text>
<text id="20484">Knight Slayer's Ring+4</text>
<text id="20485">Knight Slayer's Ring+5</text>
<text id="20486">%null%</text>
<text id="20487">%null%</text>
<text id="20488">%null%</text>
<text id="20489">%null%</text>
<text id="20490">Magic Clutch Ring</text>
<text id="20491">Magic Clutch Ring+1</text>
<text id="20492">Magic Clutch Ring+2</text>
<text id="20493">Magic Clutch Ring+3</text>
<text id="20494">Magic Clutch Ring+4</text>
<text id="20495">Magic Clutch Ring+5</text>
<text id="20496">%null%</text>
<text id="20497">%null%</text>
<text id="20498">%null%</text>
<text id="20499">%null%</text>
<text id="20500">Lightning Clutch Ring</text>
<text id="20501">Lightning Clutch Ring+1</text>
<text id="20502">Lightning Clutch Ring+2</text>
<text id="20503">Lightning Clutch Ring+3</text>
<text id="20504">Lightning Clutch Ring+4</text>
<text id="20505">Lightning Clutch Ring+5</text>
<text id="20506">%null%</text>
<text id="20507">%null%</text>
<text id="20508">%null%</text>
<text id="20509">%null%</text>
<text id="20510">Fire Clutch Ring</text>
<text id="20511">Fire Clutch Ring+1</text>
<text id="20512">Fire Clutch Ring+2</text>
<text id="20513">Fire Clutch Ring+3</text>
<text id="20514">Fire Clutch Ring+4</text>
<text id="20515">Fire Clutch Ring+5</text>
<text id="20516">%null%</text>
<text id="20517">%null%</text>
<text id="20518">%null%</text>
<text id="20519">%null%</text>
<text id="20520">Dark Clutch Ring</text>
<text id="20521">Dark Clutch Ring+1</text>
<text id="20522">Dark Clutch Ring+2</text>
<text id="20523">Dark Clutch Ring+3</text>
<text id="20524">Dark Clutch Ring+4</text>
<text id="20525">Dark Clutch Ring+5</text>
<text id="20526">%null%</text>
<text id="20527">%null%</text>
<text id="20528">%null%</text>
<text id="20529">%null%</text>
<text id="20530">%null%</text>
<text id="20531">%null%</text>
<text id="20532">%null%</text>
<text id="20533">%null%</text>
<text id="20534">%null%</text>
<text id="20535">%null%</text>
<text id="20536">%null%</text>
<text id="20537">%null%</text>
<text id="20538">%null%</text>
<text id="20539">%null%</text>
<text id="20540">Flynn's Ring</text>
<text id="20541">Flynn's Ring+1</text>
<text id="20542">Flynn's Ring+2</text>
<text id="20543">Flynn's Ring+3</text>
<text id="20544">Flynn's Ring+4</text>
<text id="20545">Flynn's Ring+5</text>
<text id="20546">%null%</text>
<text id="20547">%null%</text>
<text id="20548">%null%</text>
<text id="20549">%null%</text>
<text id="20550">Prisoner's Chain</text>
<text id="20551">Prisoner's Chain+1</text>
<text id="20552">Prisoner's Chain+2</text>
<text id="20553">Prisoner's Chain+3</text>
<text id="20554">Prisoner's Chain+4</text>
<text id="20555">Prisoner's Chain+5</text>
<text id="20556">%null%</text>
<text id="20557">%null%</text>
<text id="20558">%null%</text>
<text id="20559">%null%</text>
<text id="20560">%null%</text>
<text id="20561">%null%</text>
<text id="20562">%null%</text>
<text id="20563">%null%</text>
<text id="20564">%null%</text>
<text id="20565">%null%</text>
<text id="20566">%null%</text>
<text id="20567">%null%</text>
<text id="20568">%null%</text>
<text id="20569">%null%</text>
<text id="20570">%null%</text>
<text id="20571">%null%</text>
<text id="20572">%null%</text>
<text id="20573">%null%</text>
<text id="20574">%null%</text>
<text id="20575">%null%</text>
<text id="20576">%null%</text>
<text id="20577">%null%</text>
<text id="20578">%null%</text>
<text id="20579">%null%</text>
<text id="20580">Obscuring Ring</text>
<text id="20581">%null%</text>
<text id="20582">%null%</text>
<text id="20583">%null%</text>
<text id="20584">%null%</text>
<text id="20585">%null%</text>
<text id="20586">%null%</text>
<text id="20587">%null%</text>
<text id="20588">%null%</text>
<text id="20589">%null%</text>
<text id="20590">Ring of the Evil Eye</text>
<text id="20591">Ring of the Evil Eye+1</text>
<text id="20592">Ring of the Evil Eye+2</text>
<text id="20593">Ring of the Evil Eye+3</text>
<text id="20594">Ring of the Evil Eye+4</text>
<text id="20595">Ring of the Evil Eye+5</text>
<text id="20596">%null%</text>
<text id="20597">%null%</text>
<text id="20598">%null%</text>
<text id="20599">%null%</text>
<text id="20600">Ring of Calamity</text>
<text id="20601">Ring of Calamity+1</text>
<text id="20602">Ring of Calamity+2</text>
<text id="20603">Ring of Calamity+3</text>
<text id="20604">Ring of Calamity+4</text>
<text id="20605">Ring of Calamity+5</text>
<text id="20606">%null%</text>
<text id="20607">%null%</text>
<text id="20608">%null%</text>
<text id="20609">%null%</text>
<text id="20610">Farron Ring</text>
<text id="20611">Farron Ring+1</text>
<text id="20612">Farron Ring+2</text>
<text id="20613">Farron Ring+3</text>
<text id="20614">Farron Ring+4</text>
<text id="20615">Farron Ring+5</text>
<text id="20616">%null%</text>
<text id="20617">%null%</text>
<text id="20618">%null%</text>
<text id="20619">%null%</text>
<text id="20620">Aldrich's Ruby</text>
<text id="20621">%null%</text>
<text id="20622">%null%</text>
<text id="20623">%null%</text>
<text id="20624">%null%</text>
<text id="20625">%null%</text>
<text id="20626">%null%</text>
<text id="20627">%null%</text>
<text id="20628">%null%</text>
<text id="20629">%null%</text>
<text id="20630">Aldrich's Sapphire</text>
<text id="20660">Lloyd's Sword Ring</text>
<text id="20661">Lloyd's Sword Ring+1</text>
<text id="20662">Lloyd's Sword Ring+2</text>
<text id="20663">Lloyd's Sword Ring+3</text>
<text id="20664">Lloyd's Sword Ring+4</text>
<text id="20665">Lloyd's Sword Ring+5</text>
<text id="20666">%null%</text>
<text id="20667">%null%</text>
<text id="20668">%null%</text>
<text id="20669">%null%</text>
<text id="20670">Lloyd's Shield Ring</text>
<text id="20671">Lloyd's Shield Ring+1</text>
<text id="20672">Lloyd's Shield Ring+2</text>
<text id="20673">Lloyd's Shield Ring+3</text>
<text id="20674">Lloyd's Shield Ring+4</text>
<text id="20675">Lloyd's Shield Ring+5</text>
<text id="20676">%null%</text>
<text id="20677">%null%</text>
<text id="20678">%null%</text>
<text id="20679">%null%</text>
<text id="20680">%null%</text>
<text id="20681">%null%</text>
<text id="20682">%null%</text>
<text id="20683">%null%</text>
<text id="20684">%null%</text>
<text id="20685">%null%</text>
<text id="20686">%null%</text>
<text id="20687">%null%</text>
<text id="20688">%null%</text>
<text id="20689">%null%</text>
<text id="20690">%null%</text>
<text id="20691">%null%</text>
<text id="20692">%null%</text>
<text id="20693">%null%</text>
<text id="20694">%null%</text>
<text id="20695">%null%</text>
<text id="20696">%null%</text>
<text id="20697">%null%</text>
<text id="20698">%null%</text>
<text id="20699">%null%</text>
<text id="20700">Estus Ring</text>
<text id="20701">Estus Ring+1</text>
<text id="20702">Estus Ring+2</text>
<text id="20703">Estus Ring+3</text>
<text id="20704">Estus Ring+4</text>
<text id="20705">Estus Ring+5</text>
<text id="20706">%null%</text>
<text id="20707">%null%</text>
<text id="20708">%null%</text>
<text id="20709">%null%</text>
<text id="20710">Focusing Ring</text>
<text id="20711">Focusing Ring+1</text>
<text id="20712">Focusing Ring+2</text>
<text id="20713">Focusing Ring+3</text>
<text id="20714">Focusing Ring+4</text>
<text id="20715">Focusing Ring+5</text>
<text id="20716">%null%</text>
<text id="20717">%null%</text>
<text id="20718">%null%</text>
<text id="20719">%null%</text>
<text id="20720">Horsehoof Ring</text>
<text id="20721">Horsehoof Ring+1</text>
<text id="20722">Horsehoof Ring+2</text>
<text id="20723">Horsehoof Ring+3</text>
<text id="20724">Horsehoof Ring+4</text>
<text id="20725">Horsehoof Ring+5</text>
<text id="20726">%null%</text>
<text id="20727">%null%</text>
<text id="20728">%null%</text>
<text id="20729">%null%</text>
<text id="20730">Carthus Bloodring</text>
<text id="20731">%null%</text>
<text id="20732">%null%</text>
<text id="20733">%null%</text>
<text id="20734">%null%</text>
<text id="20735">%null%</text>
<text id="20736">%null%</text>
<text id="20737">%null%</text>
<text id="20738">%null%</text>
<text id="20739">%null%</text>
<text id="20740">Reversal Ring</text>
<text id="20741">%null%</text>
<text id="20742">%null%</text>
<text id="20743">%null%</text>
<text id="20744">%null%</text>
<text id="20745">%null%</text>
<text id="20746">%null%</text>
<text id="20747">%null%</text>
<text id="20748">%null%</text>
<text id="20749">%null%</text>
<text id="20750">Pontiff's Right Eye</text>
<text id="20751">Pontiff's Right Eye+1</text>
<text id="20752">Pontiff's Right Eye+2</text>
<text id="20753">Pontiff's Right Eye+3</text>
<text id="20754">Pontiff's Right Eye+4</text>
<text id="20755">Pontiff's Right Eye+5</text>
<text id="20756">%null%</text>
<text id="20757">%null%</text>
<text id="20758">%null%</text>
<text id="20759">%null%</text>
<text id="20760">%null%</text>
<text id="20761">%null%</text>
<text id="20762">%null%</text>
<text id="20763">%null%</text>
<text id="20764">%null%</text>
<text id="20765">%null%</text>
<text id="20766">%null%</text>
<text id="20767">%null%</text>
<text id="20768">%null%</text>
<text id="20769">%null%</text>
<text id="20770">%null%</text>
<text id="20771">%null%</text>
<text id="20772">%null%</text>
<text id="20773">%null%</text>
<text id="20774">%null%</text>
<text id="20775">%null%</text>
<text id="20776">%null%</text>
<text id="20777">%null%</text>
<text id="20778">%null%</text>
<text id="20779">%null%</text>
<text id="20780">%null%</text>
<text id="20781">%null%</text>
<text id="20782">%null%</text>
<text id="20783">%null%</text>
<text id="20784">%null%</text>
<text id="20785">%null%</text>
<text id="20786">%null%</text>
<text id="20787">%null%</text>
<text id="20788">%null%</text>
<text id="20789">%null%</text>
<text id="20790">Pontiff's Left Eye</text>
<text id="20791">Pontiff's Left Eye+1</text>
<text id="20792">Pontiff's Left Eye+2</text>
<text id="20793">Pontiff's Left Eye+3</text>
<text id="20794">Pontiff's Left Eye+4</text>
<text id="20795">Pontiff's Left Eye+5</text>
<text id="20796">%null%</text>
<text id="20797">%null%</text>
<text id="20798">%null%</text>
<text id="20799">%null%</text>
<text id="20800">%null%</text>
<text id="20801">%null%</text>
<text id="20802">%null%</text>
<text id="20803">%null%</text>
<text id="20804">%null%</text>
<text id="20805">%null%</text>
<text id="20806">%null%</text>
<text id="20807">%null%</text>
<text id="20808">%null%</text>
<text id="20809">%null%</text>
<text id="20810">%null%</text>
<text id="20811">%null%</text>
<text id="20812">%null%</text>
<text id="20813">%null%</text>
<text id="20814">%null%</text>
<text id="20815">%null%</text>
<text id="20816">%null%</text>
<text id="20817">%null%</text>
<text id="20818">%null%</text>
<text id="20819">%null%</text>
<text id="20820">%null%</text>
<text id="20821">%null%</text>
<text id="20822">%null%</text>
<text id="20823">%null%</text>
<text id="20824">%null%</text>
<text id="20825">%null%</text>
<text id="20826">%null%</text>
<text id="20827">%null%</text>
<text id="20828">%null%</text>
<text id="20829">%null%</text>
<text id="20830">Dragonscale Ring</text>
<text id="20831">Dragonscale Ring+1</text>
<text id="20832">Dragonscale Ring+2</text>
<text id="20833">Dragonscale Ring+3</text>
<text id="20834">Dragonscale Ring+4</text>
<text id="20835">Dragonscale Ring+5</text>
<text id="20836">%null%</text>
<text id="20837">%null%</text>
<text id="20838">%null%</text>
<text id="20839">%null%</text>
<text id="20840">%null%</text>
<text id="30000">Ring of Londor</text>
<text id="30001">%null%</text>
<text id="30002">%null%</text>
<text id="30003">%null%</text>
<text id="30004">%null%</text>
<text id="30005">%null%</text>
<text id="30006">%null%</text>
<text id="30007">%null%</text>
<text id="30008">%null%</text>
<text id="30009">%null%</text>
<text id="30010">Spirit Amethyst</text>
<text id="30011">Spirit Amethyst+1</text>
<text id="30012">Spirit Amethyst+2</text>
<text id="30013">Spirit Amethyst+3</text>
<text id="30014">Spirit Amethyst+4</text>
<text id="30015">Spirit Amethyst+5</text>
<text id="30016">%null%</text>
<text id="30017">%null%</text>
<text id="30018">%null%</text>
<text id="30019">%null%</text>
<text id="30020">Unholy Remains</text>
<text id="30021">Unholy Remains+1</text>
<text id="30022">Unholy Remains+2</text>
<text id="30023">Unholy Remains+3</text>
<text id="30024">Unholy Remains+4</text>
<text id="30025">Unholy Remains+5</text>
<text id="30026">%null%</text>
<text id="30027">%null%</text>
<text id="30028">%null%</text>
<text id="30029">%null%</text>
<text id="30030">%null%</text>
<text id="30031">%null%</text>
<text id="30032">%null%</text>
<text id="30033">%null%</text>
<text id="30034">%null%</text>
<text id="30035">%null%</text>
<text id="30036">%null%</text>
<text id="30037">%null%</text>
<text id="30038">%null%</text>
<text id="30039">%null%</text>
<text id="30040">Wretched Pendant</text>
<text id="30041">%null%</text>
<text id="30042">%null%</text>
<text id="30043">%null%</text>
<text id="30044">%null%</text>
<text id="30045">%null%</text>
<text id="30046">%null%</text>
<text id="30047">%null%</text>
<text id="30048">%null%</text>
<text id="30049">%null%</text>
<text id="30050">Symbol of the Penitent</text>
<text id="30051">Symbol of the Penitent+1</text>
<text id="30052">Symbol of the Penitent+2</text>
<text id="30053">Symbol of the Penitent+3</text>
<text id="30054">Symbol of the Penitent+4</text>
<text id="30055">Symbol of the Penitent+5</text>
<text id="30056">%null%</text>
<text id="30057">%null%</text>
<text id="30058">%null%</text>
<text id="30059">%null%</text>
<text id="30060">%null%</text>
<text id="30061">%null%</text>
<text id="30062">%null%</text>
<text id="30063">%null%</text>
<text id="30064">%null%</text>
<text id="30065">%null%</text>
<text id="30066">%null%</text>
<text id="30067">%null%</text>
<text id="30068">%null%</text>
<text id="30069">%null%</text>
<text id="30070">Runic Seal</text>
<text id="30071">%null%</text>
<text id="30072">%null%</text>
<text id="30073">%null%</text>
<text id="30074">%null%</text>
<text id="30075">%null%</text>
<text id="30076">%null%</text>
<text id="30077">%null%</text>
<text id="30078">%null%</text>
<text id="30079">%null%</text>
<text id="30080">Tome of Sunlight</text>
<text id="30081">Tome of Sunlight+1</text>
<text id="30082">Tome of Sunlight+2</text>
<text id="30083">Tome of Sunlight+3</text>
<text id="30084">Tome of Sunlight+4</text>
<text id="30085">Tome of Sunlight+5</text>
<text id="30086">%null%</text>
<text id="30087">%null%</text>
<text id="30088">%null%</text>
<text id="30089">%null%</text>
<text id="30090">Greatwood Remnants</text>
<text id="30091">%null%</text>
<text id="30092">%null%</text>
<text id="30093">%null%</text>
<text id="30094">%null%</text>
<text id="30095">%null%</text>
<text id="30096">%null%</text>
<text id="30097">%null%</text>
<text id="30098">%null%</text>
<text id="30099">%null%</text>
<text id="30100">%null%</text>
<text id="30101">%null%</text>
<text id="30102">%null%</text>
<text id="30103">%null%</text>
<text id="30104">%null%</text>
<text id="30105">%null%</text>
<text id="30106">%null%</text>
<text id="30107">%null%</text>
<text id="30108">%null%</text>
<text id="30109">%null%</text>
<text id="30110">%null%</text>
<text id="30111">%null%</text>
<text id="30112">%null%</text>
<text id="30113">%null%</text>
<text id="30114">%null%</text>
<text id="30115">%null%</text>
<text id="30116">%null%</text>
<text id="30117">%null%</text>
<text id="30118">%null%</text>
<text id="30119">%null%</text>
<text id="30120">%null%</text>
<text id="30121">%null%</text>
<text id="30122">%null%</text>
<text id="30123">%null%</text>
<text id="30124">%null%</text>
<text id="30125">%null%</text>
<text id="30126">%null%</text>
<text id="30127">%null%</text>
<text id="30128">%null%</text>
<text id="30129">%null%</text>
<text id="30130">%null%</text>
<text id="30131">%null%</text>
<text id="30132">%null%</text>
<text id="30133">%null%</text>
<text id="30134">%null%</text>
<text id="30135">%null%</text>
<text id="30136">%null%</text>
<text id="30137">%null%</text>
<text id="30138">%null%</text>
<text id="30139">%null%</text>
<text id="30140">%null%</text>
<text id="30141">%null%</text>
<text id="30142">%null%</text>
<text id="30143">%null%</text>
<text id="30144">%null%</text>
<text id="30145">%null%</text>
<text id="30146">%null%</text>
<text id="30147">%null%</text>
<text id="30148">%null%</text>
<text id="30149">%null%</text>
<text id="30150">%null%</text>
<text id="30151">%null%</text>
<text id="30152">%null%</text>
<text id="30153">%null%</text>
<text id="30154">%null%</text>
<text id="30155">%null%</text>
<text id="30156">%null%</text>
<text id="30157">%null%</text>
<text id="30158">%null%</text>
<text id="30159">%null%</text>
<text id="30160">%null%</text>
<text id="30161">%null%</text>
<text id="30162">%null%</text>
<text id="30163">%null%</text>
<text id="30164">%null%</text>
<text id="30165">%null%</text>
<text id="30166">%null%</text>
<text id="30167">%null%</text>
<text id="30168">%null%</text>
<text id="30169">%null%</text>
<text id="30170">Demonsbane Ring</text>
<text id="30171">Demonsbane Ring+1</text>
<text id="30172">Demonsbane Ring+2</text>
<text id="30173">Demonsbane Ring+3</text>
<text id="30174">Demonsbane Ring+4</text>
<text id="30175">Demonsbane Ring+5</text>
<text id="30176">%null%</text>
<text id="30177">%null%</text>
<text id="30178">%null%</text>
<text id="30179">%null%</text>
<text id="30180">Crypt Ring</text>
<text id="30181">Crypt Ring+1</text>
<text id="30182">Crypt Ring+2</text>
<text id="30183">Crypt Ring+3</text>
<text id="30184">Crypt Ring+4</text>
<text id="30185">Crypt Ring+5</text>
<text id="30186">%null%</text>
<text id="30187">%null%</text>
<text id="30188">%null%</text>
<text id="30189">%null%</text>
<text id="30190">Blight Ring</text>
<text id="30191">Blight Ring+1</text>
<text id="30192">Blight Ring+2</text>
<text id="30193">Blight Ring+3</text>
<text id="30194">Blight Ring+4</text>
<text id="30195">Blight Ring+5</text>
<text id="30196">%null%</text>
<text id="30197">%null%</text>
<text id="30198">%null%</text>
<text id="30199">%null%</text>
<text id="30200">Hallowed Ring</text>
<text id="30201">Hallowed Ring+1</text>
<text id="30202">Hallowed Ring+2</text>
<text id="30203">Hallowed Ring+3</text>
<text id="30204">Hallowed Ring+4</text>
<text id="30205">Hallowed Ring+5</text>
<text id="30206">%null%</text>
<text id="30207">%null%</text>
<text id="30208">%null%</text>
<text id="30209">%null%</text>
<text id="30210">Ring of Wisdom</text>
<text id="30211">Ring of Wisdom+1</text>
<text id="30212">Ring of Wisdom+2</text>
<text id="30213">Ring of Wisdom+3</text>
<text id="30214">Ring of Wisdom+4</text>
<text id="30215">Ring of Wisdom+5</text>
<text id="30216">%null%</text>
<text id="30217">%null%</text>
<text id="30218">%null%</text>
<text id="30219">%null%</text>
<text id="30220">%null%</text>
<text id="30221">%null%</text>
<text id="30222">%null%</text>
<text id="30223">%null%</text>
<text id="30224">%null%</text>
<text id="30225">%null%</text>
<text id="30226">%null%</text>
<text id="30227">%null%</text>
<text id="30228">%null%</text>
<text id="30229">%null%</text>
<text id="30230">%null%</text>
<text id="30231">%null%</text>
<text id="30232">%null%</text>
<text id="30233">%null%</text>
<text id="30234">%null%</text>
<text id="30235">%null%</text>
<text id="30236">%null%</text>
<text id="30237">%null%</text>
<text id="30238">%null%</text>
<text id="30239">%null%</text>
<text id="30240">%null%</text>
<text id="30241">%null%</text>
<text id="30242">%null%</text>
<text id="30243">%null%</text>
<text id="30244">%null%</text>
<text id="30245">%null%</text>
<text id="30246">%null%</text>
<text id="30247">%null%</text>
<text id="30248">%null%</text>
<text id="30249">%null%</text>
<text id="30250">%null%</text>
<text id="30251">%null%</text>
<text id="30252">%null%</text>
<text id="30253">%null%</text>
<text id="30254">%null%</text>
<text id="30255">%null%</text>
<text id="30256">%null%</text>
<text id="30257">%null%</text>
<text id="30258">%null%</text>
<text id="30259">%null%</text>
<text id="30260">%null%</text>
<text id="30261">%null%</text>
<text id="30262">%null%</text>
<text id="30263">%null%</text>
<text id="30264">%null%</text>
<text id="30265">%null%</text>
<text id="30266">%null%</text>
<text id="30267">%null%</text>
<text id="30268">%null%</text>
<text id="30269">%null%</text>
<text id="30270">%null%</text>
<text id="30271">%null%</text>
<text id="30272">%null%</text>
<text id="30273">%null%</text>
<text id="30274">%null%</text>
<text id="30275">%null%</text>
<text id="30276">%null%</text>
<text id="30277">%null%</text>
<text id="30278">%null%</text>
<text id="30279">%null%</text>
<text id="30280">%null%</text>
<text id="30281">%null%</text>
<text id="30282">%null%</text>
<text id="30283">%null%</text>
<text id="30284">%null%</text>
<text id="30285">%null%</text>
<text id="30286">%null%</text>
<text id="30287">%null%</text>
<text id="30288">%null%</text>
<text id="30289">%null%</text>
<text id="30290">%null%</text>
<text id="30291">%null%</text>
<text id="30292">%null%</text>
<text id="30293">%null%</text>
<text id="30294">%null%</text>
<text id="30295">%null%</text>
<text id="30296">%null%</text>
<text id="30297">%null%</text>
<text id="30298">%null%</text>
<text id="30299">%null%</text>
<text id="30300">%null%</text>
<text id="30301">%null%</text>
<text id="30302">%null%</text>
<text id="30303">%null%</text>
<text id="30304">%null%</text>
<text id="30305">%null%</text>
<text id="30306">%null%</text>
<text id="30307">%null%</text>
<text id="30308">%null%</text>
<text id="30309">%null%</text>
<text id="30310">%null%</text>
<text id="30311">%null%</text>
<text id="30312">%null%</text>
<text id="30313">%null%</text>
<text id="30314">%null%</text>
<text id="30315">%null%</text>
<text id="30316">%null%</text>
<text id="30317">%null%</text>
<text id="30318">%null%</text>
<text id="30319">%null%</text>
<text id="30320">%null%</text>
<text id="30321">%null%</text>
<text id="30322">%null%</text>
<text id="30323">%null%</text>
<text id="30324">%null%</text>
<text id="30325">%null%</text>
<text id="30326">%null%</text>
<text id="30327">%null%</text>
<text id="30328">%null%</text>
<text id="30329">%null%</text>
<text id="30330">Ring of Retaliation</text>
<text id="30331">Ring of Retaliation+1</text>
<text id="30332">Ring of Retaliation+2</text>
<text id="30333">Ring of Retaliation+3</text>
<text id="30334">Ring of Retaliation+4</text>
<text id="30335">Ring of Retaliation+5</text>
<text id="30336">%null%</text>
<text id="30337">%null%</text>
<text id="30338">%null%</text>
<text id="30339">%null%</text>
<text id="30340">Ring of Reprisal</text>
<text id="30341">Ring of Reprisal+1</text>
<text id="30342">Ring of Reprisal+2</text>
<text id="30343">Ring of Reprisal+3</text>
<text id="30344">Ring of Reprisal+4</text>
<text id="30345">Ring of Reprisal+5</text>
<text id="30346">%null%</text>
<text id="30347">%null%</text>
<text id="30348">%null%</text>
<text id="30349">%null%</text>
<text id="30350">Ring of Spite</text>
<text id="30351">Ring of Spite+1</text>
<text id="30352">Ring of Spite+2</text>
<text id="30353">Ring of Spite+3</text>
<text id="30354">Ring of Spite+4</text>
<text id="30355">Ring of Spite+5</text>
<text id="30356">%null%</text>
<text id="30357">%null%</text>
<text id="30358">%null%</text>
<text id="30359">%null%</text>
<text id="30360">Ring of Retribution</text>
<text id="30361">Ring of Retribution+1</text>
<text id="30362">Ring of Retribution+2</text>
<text id="30363">Ring of Retribution+3</text>
<text id="30364">Ring of Retribution+4</text>
<text id="30365">Ring of Retribution+5</text>
<text id="30366">%null%</text>
<text id="30367">%null%</text>
<text id="30368">%null%</text>
<text id="30369">%null%</text>
<text id="30370">Ring of Vengeance</text>
<text id="30371">Ring of Vengeance+1</text>
<text id="30372">Ring of Vengeance+2</text>
<text id="30373">Ring of Vengeance+3</text>
<text id="30374">Ring of Vengeance+4</text>
<text id="30375">Ring of Vengeance+5</text>
<text id="30376">%null%</text>
<text id="30377">%null%</text>
<text id="30378">%null%</text>
<text id="30379">%null%</text>
<text id="30380">Bulwark Ring</text>
<text id="30381">%null%</text>
<text id="30382">%null%</text>
<text id="30383">%null%</text>
<text id="30384">%null%</text>
<text id="30385">%null%</text>
<text id="30386">%null%</text>
<text id="30387">%null%</text>
<text id="30388">%null%</text>
<text id="30389">%null%</text>
<text id="30390">Mercenary Ring</text>
<text id="30391">Mercenary Ring+1</text>
<text id="30392">Mercenary Ring+2</text>
<text id="30393">Mercenary Ring+3</text>
<text id="30394">Mercenary Ring+4</text>
<text id="30395">Mercenary Ring+5</text>
<text id="30396">%null%</text>
<text id="30397">%null%</text>
<text id="30398">%null%</text>
<text id="30399">%null%</text>
<text id="30400">Heretic Ring</text>
<text id="30401">Heretic Ring+1</text>
<text id="30402">Heretic Ring+2</text>
<text id="30403">Heretic Ring+3</text>
<text id="30404">Heretic Ring+4</text>
<text id="30405">Heretic Ring+5</text>
<text id="30406">%null%</text>
<text id="30407">%null%</text>
<text id="30408">%null%</text>
<text id="30409">%null%</text>
<text id="30410">Merchant Ring</text>
<text id="30411">Merchant Ring+1</text>
<text id="30412">Merchant Ring+2</text>
<text id="30413">Merchant Ring+3</text>
<text id="30414">Merchant Ring+4</text>
<text id="30415">Merchant Ring+5</text>
<text id="30416">%null%</text>
<text id="30417">%null%</text>
<text id="30418">%null%</text>
<text id="30419">%null%</text>
<text id="30420">Physician Ring</text>
<text id="30421">Physician Ring+1</text>
<text id="30422">Physician Ring+2</text>
<text id="30423">Physician Ring+3</text>
<text id="30424">Physician Ring+4</text>
<text id="30425">Physician Ring+5</text>
<text id="30426">%null%</text>
<text id="30427">%null%</text>
<text id="30428">%null%</text>
<text id="30429">%null%</text>
<text id="30430">Jester Ring</text>
<text id="30431">Jester Ring+1</text>
<text id="30432">Jester Ring+2</text>
<text id="30433">Jester Ring+3</text>
<text id="30434">Jester Ring+4</text>
<text id="30435">Jester Ring+5</text>
<text id="30436">%null%</text>
<text id="30437">%null%</text>
<text id="30438">%null%</text>
<text id="30439">%null%</text>
<text id="30440">%null%</text>
<text id="30450">Londor Tincture</text>
<text id="30451">Londor Tincture+1</text>
<text id="30452">Londor Tincture+2</text>
<text id="30453">Londor Tincture+3</text>
<text id="30454">Londor Tincture+4</text>
<text id="30455">Londor Tincture+5</text>
<text id="30460">%null%</text>
<text id="30461">%null%</text>
<text id="30462">%null%</text>
<text id="30463">%null%</text>
<text id="30464">%null%</text>
<text id="30465">%null%</text>
<text id="30470">%null%</text>
<text id="30480">%null%</text>
<text id="30490">%null%</text>
<text id="30500">Old Pygmy Brooch</text>
<text id="30501">Old Pygmy Brooch+1</text>
<text id="30502">Old Pygmy Brooch+2</text>
<text id="30503">Old Pygmy Brooch+3</text>
<text id="30504">Old Pygmy Brooch+4</text>
<text id="30505">Old Pygmy Brooch+5</text>
<text id="30510">Cursed Ring of Evasion</text>
<text id="30511">%null%</text>
<text id="30512">%null%</text>
<text id="30513">%null%</text>
<text id="30514">%null%</text>
<text id="30515">%null%</text>
<text id="30520">Cursed Ring of Vengeance</text>
<text id="30521">%null%</text>
<text id="30522">%null%</text>
<text id="30523">%null%</text>
<text id="30524">%null%</text>
<text id="30525">%null%</text>
<text id="30530">Cursed Ring of Deflection</text>
<text id="30531">%null%</text>
<text id="30532">%null%</text>
<text id="30533">%null%</text>
<text id="30534">%null%</text>
<text id="30535">%null%</text>
<text id="30540">Cursed Ring of Confusion</text>
<text id="30541">%null%</text>
<text id="30542">%null%</text>
<text id="30543">%null%</text>
<text id="30544">%null%</text>
<text id="30545">%null%</text>
<text id="30550">%null%</text>
<text id="30551">%null%</text>
<text id="30552">%null%</text>
<text id="30553">%null%</text>
<text id="30554">%null%</text>
<text id="30555">%null%</text>
<text id="30560">Redeye Ring</text>
<text id="30650">Bestial Band</text>
<text id="30651">Bestial Band+1</text>
<text id="30652">Bestial Band+2</text>
<text id="30653">Bestial Band+3</text>
<text id="30654">Bestial Band+4</text>
<text id="30655">Bestial Band+5</text>
<text id="30660">Band of Stone</text>
<text id="30661">Band of Stone+1</text>
<text id="30662">Band of Stone+2</text>
<text id="30663">Band of Stone+3</text>
<text id="30664">Band of Stone+4</text>
<text id="30665">Band of Stone+5</text>
<text id="30670">Band of Magic</text>
<text id="30671">Band of Magic+1</text>
<text id="30672">Band of Magic+2</text>
<text id="30673">Band of Magic+3</text>
<text id="30674">Band of Magic+4</text>
<text id="30675">Band of Magic+5</text>
<text id="30680">Band of Flame</text>
<text id="30681">Band of Flame+1</text>
<text id="30682">Band of Flame+2</text>
<text id="30683">Band of Flame+3</text>
<text id="30684">Band of Flame+4</text>
<text id="30685">Band of Flame+5</text>
<text id="30690">Band of Sparks</text>
<text id="30691">Band of Sparks+1</text>
<text id="30692">Band of Sparks+2</text>
<text id="30693">Band of Sparks+3</text>
<text id="30694">Band of Sparks+4</text>
<text id="30695">Band of Sparks+5</text>
<text id="30700">Band of Darkness</text>
<text id="30701">Band of Darkness+1</text>
<text id="30702">Band of Darkness+2</text>
<text id="30703">Band of Darkness+3</text>
<text id="30704">Band of Darkness+4</text>
<text id="30705">Band of Darkness+5</text>
<text id="30800">Elden Ring</text>
<text id="30801">Elden Ring+1</text>
<text id="30802">Elden Ring+2</text>
<text id="30803">Elden Ring+3</text>
<text id="30804">Elden Ring+4</text>
<text id="30805">Elden Ring+5</text>
<text id="30840">Fool's Sigil</text>
<text id="30870">Ring of Momentum</text>
<text id="30880">Ring of Grace</text>
<text id="30890">Ring of Punishment</text>
<text id="30891">Ring of Punishment+1</text>
<text id="30892">Ring of Punishment+2</text>
<text id="30893">Ring of Punishment+3</text>
<text id="30894">Ring of Punishment+4</text>
<text id="30895">Ring of Punishment+5</text>
<text id="30900">Dashmaster's String</text>
<text id="30910">Relic of Power</text>
<text id="30911">Relic of Power+1</text>
<text id="30912">Relic of Power+2</text>
<text id="30913">Relic of Power+3</text>
<text id="30914">Relic of Power+4</text>
<text id="30915">Relic of Power+5</text>
<text id="30920">Relic of Insanity</text>
<text id="30921">Relic of Insanity+1</text>
<text id="30922">Relic of Insanity+2</text>
<text id="30923">Relic of Insanity+3</text>
<text id="30924">Relic of Insanity+4</text>
<text id="30925">Relic of Insanity+5</text>
<text id="30930">Tainted Chalice</text>
<text id="30931">Tainted Chalice+1</text>
<text id="30932">Tainted Chalice+2</text>
<text id="30933">Tainted Chalice+3</text>
<text id="30934">Tainted Chalice+4</text>
<text id="30935">Tainted Chalice+5</text>
<text id="30940">Accursed Sigil</text>
<text id="30941">Accursed Sigil+1</text>
<text id="30942">Accursed Sigil+2</text>
<text id="30943">Accursed Sigil+3</text>
<text id="30944">Accursed Sigil+4</text>
<text id="30945">Accursed Sigil+5</text>
<text id="30950">Frostflower Ring</text>
<text id="30951">Frostflower Ring+1</text>
<text id="30952">Frostflower Ring+2</text>
<text id="30953">Frostflower Ring+3</text>
<text id="30954">Frostflower Ring+4</text>
<text id="30955">Frostflower Ring+5</text>
<text id="30960">Rare Ring of Humanity</text>
<text id="30970">Gwynevere's Urn</text>
<text id="30980">Dial of Obedience</text>
<text id="30981">Dial of Obedience+1</text>
<text id="30982">Dial of Obedience+2</text>
<text id="30983">Dial of Obedience+3</text>
<text id="30984">Dial of Obedience+4</text>
<text id="30985">Dial of Obedience+5</text>
<text id="30990">Offering of Might</text>
<text id="30991">Offering of Might+1</text>
<text id="30992">Offering of Might+2</text>
<text id="30993">Offering of Might+3</text>
<text id="30994">Offering of Might+4</text>
<text id="30995">Offering of Might+5</text>
<text id="31000">Offering of Tenacity</text>
<text id="31001">Offering of Tenacity+1</text>
<text id="31002">Offering of Tenacity+2</text>
<text id="31003">Offering of Tenacity+3</text>
<text id="31004">Offering of Tenacity+4</text>
<text id="31005">Offering of Tenacity+5</text>
<text id="31010">Offering of Fortitude</text>
<text id="31011">Offering of Fortitude+1</text>
<text id="31012">Offering of Fortitude+2</text>
<text id="31013">Offering of Fortitude+3</text>
<text id="31014">Offering of Fortitude+4</text>
<text id="31015">Offering of Fortitude+5</text>
<text id="31020">Offering of Vitality</text>
<text id="31021">Offering of Vitality+1</text>
<text id="31022">Offering of Vitality+2</text>
<text id="31023">Offering of Vitality+3</text>
<text id="31024">Offering of Vitality+4</text>
<text id="31025">Offering of Vitality+5</text>
<text id="31030">Offering of Devotion</text>
<text id="31031">Offering of Devotion+1</text>
<text id="31032">Offering of Devotion+2</text>
<text id="31033">Offering of Devotion+3</text>
<text id="31034">Offering of Devotion+4</text>
<text id="31035">Offering of Devotion+5</text>
<text id="31040">Offering of Fervor</text>
<text id="31041">Offering of Fervor+1</text>
<text id="31042">Offering of Fervor+2</text>
<text id="31043">Offering of Fervor+3</text>
<text id="31044">Offering of Fervor+4</text>
<text id="31045">Offering of Fervor+5</text>
<text id="31050">Ravenous Chalice</text>
<text id="31060">Relic of Legends</text>
<text id="31061">Relic of Legends+1</text>
<text id="31062">Relic of Legends+2</text>
<text id="31063">Relic of Legends+3</text>
<text id="31064">Relic of Legends+4</text>
<text id="31065">Relic of Legends+5</text>
<text id="31070">Relic of Myths</text>
<text id="31071">Relic of Myths+1</text>
<text id="31072">Relic of Myths+2</text>
<text id="31073">Relic of Myths+3</text>
<text id="31074">Relic of Myths+4</text>
<text id="31075">Relic of Myths+5</text>
<text id="31080">Old Man's Gambit</text>
</entries>
</fmg>